odoo8_addon_l10n_es_partner_mercantil-8.0.1.0.0.99.dev9-py2.7-nspkg.pth
odoo8_addon_l10n_es_partner_mercantil-8.0.1.0.0.99.dev9.dist-info/DESCRIPTION.rst
odoo8_addon_l10n_es_partner_mercantil-8.0.1.0.0.99.dev9.dist-info/METADATA
odoo8_addon_l10n_es_partner_mercantil-8.0.1.0.0.99.dev9.dist-info/RECORD
odoo8_addon_l10n_es_partner_mercantil-8.0.1.0.0.99.dev9.dist-info/WHEEL
odoo8_addon_l10n_es_partner_mercantil-8.0.1.0.0.99.dev9.dist-info/metadata.json
odoo8_addon_l10n_es_partner_mercantil-8.0.1.0.0.99.dev9.dist-info/namespace_packages.txt
odoo8_addon_l10n_es_partner_mercantil-8.0.1.0.0.99.dev9.dist-info/top_level.txt
odoo_addons/l10n_es_partner_mercantil/__init__.py
odoo_addons/l10n_es_partner_mercantil/__openerp__.py
odoo_addons/l10n_es_partner_mercantil/i18n/bg.po
odoo_addons/l10n_es_partner_mercantil/i18n/ca.po
odoo_addons/l10n_es_partner_mercantil/i18n/cs.po
odoo_addons/l10n_es_partner_mercantil/i18n/en_US.po
odoo_addons/l10n_es_partner_mercantil/i18n/es.po
odoo_addons/l10n_es_partner_mercantil/i18n/es_CR.po
odoo_addons/l10n_es_partner_mercantil/i18n/eu.po
odoo_addons/l10n_es_partner_mercantil/i18n/fr.po
odoo_addons/l10n_es_partner_mercantil/i18n/gl.po
odoo_addons/l10n_es_partner_mercantil/i18n/hr.po
odoo_addons/l10n_es_partner_mercantil/i18n/l10n_es_partner_mercantil.pot
odoo_addons/l10n_es_partner_mercantil/i18n/nl.po
odoo_addons/l10n_es_partner_mercantil/i18n/pl.po
odoo_addons/l10n_es_partner_mercantil/i18n/pt.po
odoo_addons/l10n_es_partner_mercantil/i18n/pt_BR.po
odoo_addons/l10n_es_partner_mercantil/i18n/ru.po
odoo_addons/l10n_es_partner_mercantil/i18n/sl.po
odoo_addons/l10n_es_partner_mercantil/i18n/sv.po
odoo_addons/l10n_es_partner_mercantil/i18n/tr.po
odoo_addons/l10n_es_partner_mercantil/i18n/vi.po
odoo_addons/l10n_es_partner_mercantil/models/__init__.py
odoo_addons/l10n_es_partner_mercantil/models/partner_es.py
odoo_addons/l10n_es_partner_mercantil/static/description/icon.png
odoo_addons/l10n_es_partner_mercantil/static/description/icon.svg
odoo_addons/l10n_es_partner_mercantil/views/partner_es_view.xml
